[{"id":4181,"vol":1,"day":33,"w":"jaundiced","m":"편견을 가진 / 황달에 걸린","p":[{"d":"편견을 가진","s":["prejudiced","biased","mistrustful"]},{"d":"황달에 걸린","s":["icteric","distorted"]}],"s":["prejudiced","biased","mistrustful","icteric","distorted"],"r":"[프랑스어] jaune(yellow/노란색) + -ed → 황달로 노랗게 된 → 황달에 걸린, 편견을 가진","type":"word","src":"Y"},{"id":4182,"vol":1,"day":33,"w":"jaunt","m":"짧은 여행 / 소풍 / 소풍을 가다","p":[{"d":"짧은 여행 / 소풍","s":["outing","excursion"]}],"s":["outing","excursion"],"r":"","type":"word","src":"Y"},{"id":4183,"vol":1,"day":33,"w":"javelin","m":"투창 / 창","p":[{"d":"투창 / 창","s":["spear","dart","harpoon","lance"]}],"s":["spear","dart","harpoon","lance"],"r":"[고대 프랑스어] javeline(small spear/작은 창) → 던지는 작은 창 → 던지는 창","type":"word","src":"Y"},{"id":4184,"vol":1,"day":33,"w":"jaywalk","m":"무단 횡단하다","p":[{"d":"무단 횡단하다","s":["cross a street illegally"]}],"s":["cross a street illegally"],"r":"jay(jay/어치새, 촌뜨기) + walk(walk/걷다) → 촌뜨기처럼 무단으로 걷다 → 무단횡단하다","type":"word","src":"Y"},{"id":4185,"vol":1,"day":33,"w":"jejune","m":"미숙한 / 무미건조한 / 불모의 / 영양분이 없는","p":[{"d":"미숙한","s":["puerile"]},{"d":"무미건조한","s":["dry"]},{"d":"불모의 / 영양분이 없는","s":["immature","meager","dull","insipid"]}],"s":["puerile","dry","immature","meager","dull","insipid"],"r":"[라틴어] jejunus(fasting/공복의) → 배가 비어 빈약한 → 미숙한, 재미없는","type":"word","src":"Y"},{"id":4186,"vol":1,"day":33,"w":"jeopardize","m":"위태롭게 하다","p":[{"d":"위태롭게 하다","s":["endanger","imperil"]}],"s":["endanger","imperil"],"r":"","type":"word","src":"Y"},{"id":4187,"vol":1,"day":33,"w":"jest","m":"농담 / 조롱","p":[{"d":"농담","s":["joke"]},{"d":"조롱","s":["prank","banter","deride","jeer","kid","mock"]}],"s":["joke","prank","banter","deride","jeer","kid","mock"],"r":"[고대 프랑스어] geste(deed/행위) → 재미있는 행위 → 농담, 농담하다","type":"word","src":"Y"},{"id":4188,"vol":1,"day":33,"w":"jet lag","m":"비행기 시차(時差) 피로","p":[],"s":[],"r":"","type":"phrase","src":"Y"},{"id":4189,"vol":1,"day":33,"w":"jettison","m":"내던지다 / 버리다","p":[{"d":"내던지다 / 버리다","s":["discard","dump","scrap"]}],"s":["discard","dump","scrap"],"r":"jett(throw/던지다) + -ison → 던져버리다 → 짐을 버리다","type":"word","src":"Y"},{"id":4190,"vol":1,"day":33,"w":"Jim Crow","m":"흑인 차별 정책","p":[],"s":[],"r":"","type":"phrase","src":"Y"},{"id":4191,"vol":1,"day":33,"w":"jingoism","m":"호전적 애국주의","p":[],"s":[],"r":"","type":"word","src":"Y"},{"id":4192,"vol":1,"day":33,"w":"jobless","m":"실직한","p":[{"d":"실직한","s":["unemployed"]}],"s":["unemployed"],"r":"","type":"word","src":"Y"},{"id":4193,"vol":1,"day":33,"w":"jocular","m":"익살스러운 / 우스꽝스러운","p":[{"d":"익살스러운","s":["humorous"]},{"d":"우스꽝스러운","s":["facetious","joking"]}],"s":["humorous","facetious","joking"],"r":"jocul(joke/농담) + -ar → 농담의 성질 → 익살맞은, 유머러스한","type":"word","src":"Y"},{"id":4194,"vol":1,"day":33,"w":"jolt","m":"덜컹거리게 하다 / 충격을 주다 / 급격한 충격","p":[{"d":"덜컹거리게 하다","s":["shake"]}],"s":["shake"],"r":"","type":"word","src":"Y"},{"id":4195,"vol":1,"day":33,"w":"jostle","m":"밀어제치다","p":[{"d":"밀어제치다","s":["shove","push","hustle"]}],"s":["shove","push","hustle"],"r":"joust(joust/마상 창시합) + -le → 마상 창시합처럼 부딪히다 → 밀치다, 경합하다","type":"word","src":"Y"},{"id":4196,"vol":1,"day":33,"w":"jot down","m":"적어두다","p":[{"d":"적어두다","s":["write down"]}],"s":["write down"],"r":"","type":"phrase","src":"Y"},{"id":4197,"vol":1,"day":33,"w":"jubilation","m":"환호 / 환희","p":[{"d":"환호 / 환희","s":["exultation"]}],"s":["exultation"],"r":"","type":"word","src":"Y"},{"id":4198,"vol":1,"day":33,"w":"judge","m":"재판하다 / 판단하다 / 심사하다 / 판사 / 심사 위원","p":[{"d":"재판하다 / 판단하다 / 심사하다 / 판사","s":["justice"]}],"s":["justice"],"r":"","type":"word","src":"Y"},{"id":4199,"vol":1,"day":33,"w":"judicial","m":"사법의","p":[{"d":"사법의","s":["legal","judiciary","juridical","impartial","discriminating"]}],"s":["legal","judiciary","juridical","impartial","discriminating"],"r":"jud(judge/판단하다) + -icial → 판단하는 것에 관한 → 사법의, 공정한","type":"word","src":"Y"},{"id":4200,"vol":1,"day":33,"w":"judicious","m":"분별 있는 / 현명한","p":[{"d":"분별 있는 / 현명한","s":["sagacious","wise","reasonable","sensible"]}],"s":["sagacious","wise","reasonable","sensible"],"r":"judic(judge/판단하다) + -ious → 잘 판단하는 → 현명한, 분별력 있는","type":"word","src":"Y"},{"id":4201,"vol":1,"day":33,"w":"juggernaut","m":"거대한 것 / 거대 조직 / 초대형 트럭","p":[{"d":"거대한 것","s":["leviathan"]},{"d":"거대 조직 / 초대형 트럭","s":["massive force","unstoppable power"]}],"s":["leviathan","massive force","unstoppable power"],"r":"[힌두어] Jagannath(크리슈나의 칭호) → 거대한 신의 수레 → 압도적으로 강력한 것","type":"word","src":"Y"},{"id":4202,"vol":1,"day":33,"w":"juggle","m":"병행하다(여러 일을) / 저글링하다","p":[],"s":[],"r":"","type":"word","src":"Y"},{"id":4203,"vol":1,"day":33,"w":"juice","m":"활기 / 본질","p":[{"d":"활기","s":["inspiration"]},{"d":"본질","s":["extract","fluid","liquid","nectar","core","essence","kernel","soul","sap","vitality","dope","drug","narcotic"]}],"s":["inspiration","extract","fluid","liquid","nectar","core","essence","kernel","soul","sap","vitality","dope","drug","narcotic"],"r":"[고대 프랑스어] jus(broth/즙) → 과일에서 짜낸 액체 → 주스, 즙","type":"word","src":"Y"},{"id":4204,"vol":1,"day":33,"w":"jumble","m":"마구 뒤섞다 / 엉클어 놓다 / 뒤범벅","p":[{"d":"마구 뒤섞다 / 엉클어 놓다 / 뒤범벅","s":["welter","hodgepodge","confuse","disorder","mix","clutter","mishmash","muddle"]}],"s":["welter","hodgepodge","confuse","disorder","mix","clutter","mishmash","muddle"],"r":"[중세 영어] jumblen(mix up/뒤섞다) → 뒤섞어 뒤죽박죽으로 만들다 → 혼잡, 뒤범벅","type":"word","src":"Y"},{"id":4205,"vol":1,"day":33,"w":"jump at the chance","m":"기회를 잡다","p":[],"s":[],"r":"","type":"phrase","src":"Y"},{"id":4206,"vol":1,"day":33,"w":"jump on the bandwagon","m":"시류에 편승하다","p":[{"d":"시류에 편승하다","s":["follow the majority"]}],"s":["follow the majority"],"r":"","type":"phrase","src":"Y"},{"id":4207,"vol":1,"day":33,"w":"juncture","m":"접합 / 중대한 국면 / 시기 / 위기","p":[{"d":"접합 / 중대한 국면 / 시기","s":["moment"]},{"d":"위기","s":["crisis"]}],"s":["moment","crisis"],"r":"","type":"word","src":"Y"},{"id":4208,"vol":1,"day":33,"w":"junk","m":"폐물 / 쓰레기","p":[{"d":"폐물 / 쓰레기","s":["trash","rubbish","garbage","waste","scrap"]}],"s":["trash","rubbish","garbage","waste","scrap"],"r":"[중세 영어] jonk(old rope/낡은 밧줄) → 쓸모없어진 것 → 쓰레기, 잡동사니","type":"word","src":"Y"},{"id":4209,"vol":1,"day":33,"w":"jurisprudence","m":"법학","p":[{"d":"법학","s":["legal knowledge","law"]}],"s":["legal knowledge","law"],"r":"juris(law/법) + prudence(knowledge/지식) → 법의 지식 → 법학","type":"word","src":"Y"},{"id":4210,"vol":1,"day":33,"w":"just","m":"정당한 / 정의로운 / 정확한 / 지금 막 / 꼭 / 정말 / 다만 / 간신히","p":[],"s":[],"r":"","type":"word","src":"Y"},{"id":4211,"vol":1,"day":33,"w":"just around the corner","m":"임박한 / 아주 가까운","p":[{"d":"임박한 / 아주 가까운","s":["just around the bend"]}],"s":["just around the bend"],"r":"","type":"phrase","src":"Y"},{"id":4212,"vol":1,"day":33,"w":"just as","m":"~와 꼭 마찬가지로","p":[],"s":[],"r":"","type":"phrase","src":"Y"},{"id":4213,"vol":1,"day":33,"w":"just off the boat","m":"갓 이주한 / 순진해서 속기 쉬운","p":[{"d":"갓 이주한 / 순진해서 속기 쉬운","s":["naive"]}],"s":["naive"],"r":"","type":"phrase","src":"Y"},{"id":4214,"vol":1,"day":33,"w":"justify","m":"정당성을 입증하다 / 정당화하다","p":[{"d":"정당성을 입증하다 / 정당화하다","s":["vindicate","excuse","warrant","legitimize"]}],"s":["vindicate","excuse","warrant","legitimize"],"r":"just(right/올바른) + -ify → 올바르게 만들다 → 정당화하다","type":"word","src":"Y"},{"id":4215,"vol":1,"day":33,"w":"juvenile","m":"청소년의","p":[{"d":"청소년의","s":["adolescent","young","childish","immature","infantile","puerile","child","youth"]}],"s":["adolescent","young","childish","immature","infantile","puerile","child","youth"],"r":"juven(young/젊은) + -ile → 젊은 → 청소년의, 어린애 같은","type":"word","src":"Y"},{"id":4216,"vol":1,"day":33,"w":"juxtapose","m":"나란히 놓다 / 병치하다","p":[{"d":"나란히 놓다 / 병치하다","s":["place side by side","put side by side"]}],"s":["place side by side","put side by side"],"r":"juxta(beside/옆에) + pos(place/놓다) → 옆에 나란히 놓다 → 나란히 놓다, 병치하다","type":"word","src":"Y"},{"id":4217,"vol":1,"day":33,"w":"karma","m":"업보 / 인과응보 / 특징적인 분위기","p":[{"d":"업보 / 인과응보 / 특징적인 분위기","s":["destiny","fate","kismet","atmosphere","aura"]}],"s":["destiny","fate","kismet","atmosphere","aura"],"r":"[산스크리트어] karma(action/행위) → 행위가 낳는 결과 → 인과응보, 업보","type":"word","src":"Y"},{"id":4218,"vol":1,"day":33,"w":"keen","m":"강한 / 예리한 / 예민한 / 열심인 / 열망하는 / 싼(값이)","p":[{"d":"강한 / 예리한","s":["sharp"]},{"d":"예민한 / 열심인 / 열망하는 / 싼(값이)","s":["acute","cutting","incisive","fierce","intense","perceptive","sensitive","eager","enthusiastic","fervent"]}],"s":["sharp","acute","cutting","incisive","fierce","intense","perceptive","sensitive","eager","enthusiastic","fervent"],"r":"[고대 영어] cene(bold/대담한) → 날카롭고 대담한 → 날카로운, 예민한","type":"word","src":"Y"},{"id":4219,"vol":1,"day":33,"w":"keep a cool head","m":"냉정함을 유지하다","p":[{"d":"냉정함을 유지하다","s":["keep cool"]}],"s":["keep cool"],"r":"","type":"phrase","src":"Y"},{"id":4220,"vol":1,"day":33,"w":"keep a journal","m":"일기를 쓰다","p":[],"s":[],"r":"","type":"phrase","src":"Y"},{"id":4221,"vol":1,"day":33,"w":"keep a straight face","m":"웃지 않다 / 진지한 표정을 하다","p":[{"d":"웃지 않다 / 진지한 표정을 하다","s":["look serious"]}],"s":["look serious"],"r":"","type":"phrase","src":"Y"},{"id":4222,"vol":1,"day":33,"w":"keep abreast of","m":"~(정보)에 뒤떨어지지 않다 / ~와 보조를 맞추다","p":[],"s":[],"r":"","type":"phrase","src":"Y"},{"id":4223,"vol":1,"day":33,"w":"keep an eye on","m":"감시하다 / 유의하다","p":[{"d":"감시하다","s":["watch"]}],"s":["watch"],"r":"","type":"phrase","src":"Y"},{"id":4224,"vol":1,"day":33,"w":"keep ~ at bay","m":"~를 가까이 못 오게 하다 / 저지하다","p":[],"s":[],"r":"","type":"phrase","src":"Y"},{"id":4225,"vol":1,"day":33,"w":"keep away","m":"멀리하다 / 피하다","p":[{"d":"멀리하다 / 피하다","s":["avoid","eschew","shun"]}],"s":["avoid","eschew","shun"],"r":"","type":"phrase","src":"Y"},{"id":4226,"vol":1,"day":33,"w":"keep body and soul together","m":"간신히 살아나가다","p":[],"s":[],"r":"","type":"phrase","src":"Y"},{"id":4227,"vol":1,"day":33,"w":"keep close tabs on","m":"철저히 감시하다","p":[{"d":"철저히 감시하다","s":["watch closely"]}],"s":["watch closely"],"r":"","type":"phrase","src":"Y"},{"id":4228,"vol":1,"day":33,"w":"keep ~ company","m":"~와 동행하다","p":[{"d":"~와 동행하다","s":["accompany"]}],"s":["accompany"],"r":"","type":"phrase","src":"Y"},{"id":4229,"vol":1,"day":33,"w":"keep ~ in check","m":"~을 억제하다 / 저지하다","p":[{"d":"~을 억제하다","s":["keep ~ under control"]}],"s":["keep ~ under control"],"r":"","type":"phrase","src":"Y"},{"id":4230,"vol":1,"day":33,"w":"keep ~ in mind","m":"~을 명심하다 / 기억하다","p":[{"d":"~을 명심하다 / 기억하다","s":["remember"]}],"s":["remember"],"r":"","type":"phrase","src":"Y"},{"id":4231,"vol":1,"day":33,"w":"keep ~ in order","m":"~의 질서를 바로잡아두다 / ~을 정리해두다","p":[],"s":[],"r":"","type":"phrase","src":"Y"},{"id":4232,"vol":1,"day":33,"w":"keep one's fingers crossed","m":"행운을 빌다","p":[{"d":"행운을 빌다","s":["hope for good luck"]}],"s":["hope for good luck"],"r":"","type":"phrase","src":"Y"},{"id":4233,"vol":1,"day":33,"w":"keep one's head","m":"침착함을 유지하다","p":[{"d":"침착함을 유지하다","s":["remain calm"]}],"s":["remain calm"],"r":"","type":"phrase","src":"Y"},{"id":4234,"vol":1,"day":33,"w":"keep one's head above water","m":"살아남다 / 빚지지 않고 있다","p":[],"s":[],"r":"","type":"phrase","src":"Y"},{"id":4235,"vol":1,"day":33,"w":"keep one's temper","m":"화를 참다","p":[],"s":[],"r":"","type":"phrase","src":"Y"},{"id":4236,"vol":1,"day":33,"w":"keep out of sight","m":"숨어 있다","p":[{"d":"숨어 있다","s":["lurk"]}],"s":["lurk"],"r":"","type":"phrase","src":"Y"},{"id":4237,"vol":1,"day":33,"w":"keep track of","m":"추적하다 / ~의 소식을 알고 있다","p":[],"s":[],"r":"","type":"phrase","src":"Y"},{"id":4238,"vol":1,"day":33,"w":"keep ~ under one's hat","m":"~을 비밀로 해두다","p":[],"s":[],"r":"","type":"phrase","src":"Y"},{"id":4239,"vol":1,"day":33,"w":"keep up","m":"유지하다","p":[{"d":"유지하다","s":["maintain"]}],"s":["maintain"],"r":"","type":"phrase","src":"Y"},{"id":4240,"vol":1,"day":33,"w":"keep up with","m":"~을 따라가다 / ~에 뒤떨어지지 않다 / ~와 접촉을 유지하다","p":[{"d":"~을 따라가다 / ~에 뒤떨어지지 않다","s":["remain informed about"]}],"s":["remain informed about"],"r":"","type":"phrase","src":"Y"},{"id":4241,"vol":1,"day":33,"w":"kernel","m":"핵심","p":[{"d":"핵심","s":["core","grain","nut","gist","heart","nub","pith"]}],"s":["core","grain","nut","gist","heart","nub","pith"],"r":"[고대 영어] cyrnel(seed/씨앗) → 씨앗의 알맹이 → 낟알, 핵심","type":"word","src":"Y"},{"id":4242,"vol":1,"day":33,"w":"key","m":"중요한 / 기호 설명표(지도의)","p":[],"s":[],"r":"","type":"word","src":"Y"},{"id":4243,"vol":1,"day":33,"w":"keyboard warrior","m":"키보드 전사(인터넷 공간에서는 말을 거침없이 해대는)","p":[],"s":[],"r":"","type":"phrase","src":"Y"},{"id":4244,"vol":1,"day":33,"w":"keystone","m":"핵심 / 중추 / 근본 원리","p":[],"s":[],"r":"","type":"word","src":"Y"},{"id":4245,"vol":1,"day":33,"w":"kick","m":"쾌감 / 전율 / 발길질 / 차다 / 불평하다","p":[{"d":"쾌감 / 전율","s":["thrill"]}],"s":["thrill"],"r":"","type":"word","src":"Y"},{"id":4246,"vol":1,"day":33,"w":"kick out","m":"쫓아내다 / 해고하다","p":[{"d":"쫓아내다 / 해고하다","s":["dismiss"]}],"s":["dismiss"],"r":"","type":"phrase","src":"Y"},{"id":4247,"vol":1,"day":33,"w":"kick the bucket","m":"죽다","p":[{"d":"죽다","s":["die"]}],"s":["die"],"r":"","type":"phrase","src":"Y"},{"id":4248,"vol":1,"day":33,"w":"kid","m":"아이 / 젊은이 / 놀리다 / 농담하다","p":[],"s":[],"r":"","type":"word","src":"Y"},{"id":4249,"vol":1,"day":33,"w":"kidnap","m":"유괴하다 / 납치하다","p":[{"d":"유괴하다 / 납치하다","s":["abduct","snatch"]}],"s":["abduct","snatch"],"r":"kid(kid/아이) + nap(nab/훔치다) → 아이를 훔쳐 데려가다 → 납치하다","type":"word","src":"Y"},{"id":4250,"vol":1,"day":33,"w":"kidney","m":"신장 / 콩팥","p":[],"s":[],"r":"[중세 영어, 어원 불명] kidney(kidney/신장) → 신장 → 신장, 성질","type":"word","src":"Y"},{"id":4251,"vol":1,"day":33,"w":"kindle","m":"타오르게 하다 / 부추기다","p":[{"d":"타오르게 하다 / 부추기다","s":["inspire","ignite","spark","excite","arouse"]}],"s":["inspire","ignite","spark","excite","arouse"],"r":"[고대 노르드어] kynda(light a fire/불 지르다) → 불씨에 불을 붙이다 → 불을 지피다, 자극하다","type":"word","src":"Y"},{"id":4252,"vol":1,"day":33,"w":"kindred","m":"혈연 / 친족 / 동종 / 혈연의 / 유사한 / 마음이 맞는","p":[{"d":"혈연 / 친족 / 동종 / 혈연의 / 유사한 / 마음이 맞는","s":["kin","kinsfolk","relative","affinity","likeness","semblance","akin","analogous","cognate","consaquineous","related","similar","congenial"]}],"s":["similar","congenial","kin","kinsfolk","relative","affinity","likeness","semblance","akin","analogous","cognate","consaquineous","related"],"r":"kin(family/친족) + -dred → 친족 관계인 → 친척, 동종의","type":"word","src":"Y"},{"id":4253,"vol":1,"day":33,"w":"kinetic","m":"운동의 / 활동적인","p":[{"d":"운동의 / 활동적인","s":["active"]}],"s":["active"],"r":"kine(move/움직이다) + -tic → 움직임에 관한 → 운동의","type":"word","src":"Y"},{"id":4254,"vol":1,"day":33,"w":"kiosk","m":"무인 정보 단말기 / 간이 매점","p":[],"s":[],"r":"","type":"word","src":"Y"},{"id":4255,"vol":1,"day":33,"w":"kiss ~ good-bye","m":"~에게 이별의 키스를 하다 / ~을 단념하다","p":[],"s":[],"r":"","type":"phrase","src":"Y"},{"id":4256,"vol":1,"day":33,"w":"kit","m":"도구 한 벌","p":[],"s":[],"r":"","type":"word","src":"Y"},{"id":4257,"vol":1,"day":33,"w":"kitschy","m":"천박한","p":[{"d":"천박한","s":["funny and cheap","vulgar"]}],"s":["funny and cheap","vulgar"],"r":"","type":"word","src":"Y"},{"id":4258,"vol":1,"day":33,"w":"kleptomania","m":"도벽","p":[{"d":"도벽","s":["recurrent urge to steal"]}],"s":["recurrent urge to steal"],"r":"klepto(steal/훔치다) + mania(madness/광증) → 훔치는 광증 → 도벽, 절도광","type":"word","src":"Y"},{"id":4259,"vol":1,"day":33,"w":"knack","m":"요령 / 솜씨 / 버릇","p":[{"d":"요령","s":["hang"]},{"d":"솜씨","s":["skill","talent"]},{"d":"버릇","s":["trick","aptitude"]}],"s":["hang","skill","talent","trick","aptitude"],"r":"[중세 영어] knak(trick/요령) → 능숙하게 하는 비결 → 재주, 요령","type":"word","src":"Y"},{"id":4260,"vol":1,"day":33,"w":"knavery","m":"부정 행위","p":[{"d":"부정 행위","s":["iniquity"]}],"s":["iniquity"],"r":"","type":"word","src":"Y"},{"id":4261,"vol":1,"day":33,"w":"kneel","m":"무릎을 꿇다","p":[],"s":[],"r":"","type":"word","src":"Y"},{"id":4262,"vol":1,"day":33,"w":"knickknack","m":"자질구레한 장신구","p":[{"d":"자질구레한 장신구","s":["bric-a-brac","trinket"]}],"s":["bric-a-brac","trinket"],"r":"","type":"word","src":"Y"},{"id":4263,"vol":1,"day":33,"w":"knock up","m":"급히 만들다 / 녹초가 되게 하다","p":[{"d":"급히 만들다","s":["prepare quickly"]}],"s":["prepare quickly"],"r":"","type":"phrase","src":"Y"},{"id":4264,"vol":1,"day":33,"w":"knockabout","m":"소형 요트 / 떠들썩한","p":[{"d":"소형 요트","s":["sailboat"]},{"d":"떠들썩한","s":["boisterous"]}],"s":["sailboat","boisterous"],"r":"","type":"word","src":"Y"},{"id":4265,"vol":1,"day":33,"w":"knot","m":"매듭 / 무리 / 혹 / 난제 / 핵심 / 연분 / 매다","p":[{"d":"매듭 / 무리 / 혹 / 난제 / 핵심 / 연분 / 매다","s":["gnarl","complication","difficulty","tangle","bond","connection","relation","ties"]}],"s":["gnarl","complication","difficulty","tangle","bond","connection","relation","ties"],"r":"[고대 영어] cnotta(knot/매듭) → 얽힌 매듭 → 매듭, 난제","type":"word","src":"Y"},{"id":4266,"vol":1,"day":33,"w":"know ~ like the back of one's hand","m":"~을 아주 잘 알고 있다","p":[],"s":[],"r":"","type":"phrase","src":"Y"},{"id":4267,"vol":1,"day":33,"w":"know one's way around","m":"~을 잘 알고 있다 / 지리에 밝다","p":[],"s":[],"r":"","type":"phrase","src":"Y"},{"id":4268,"vol":1,"day":33,"w":"knowingly","m":"고의로","p":[{"d":"고의로","s":["intentionally","deliberately","wittingly"]}],"s":["intentionally","deliberately","wittingly"],"r":"know(know/알다) + -ingly → 알면서 → 알고도, 고의로","type":"word","src":"Y"},{"id":4269,"vol":1,"day":33,"w":"knowledgeable","m":"아는 것이 많은 / 박식한","p":[{"d":"아는 것이 많은 / 박식한","s":["well-informed"]}],"s":["well-informed"],"r":"","type":"word","src":"Y"},{"id":4270,"vol":1,"day":33,"w":"kudos","m":"찬사 / 영광","p":[{"d":"찬사","s":["praise"]},{"d":"영광","s":["distinction","fame","glory","acclaim","applause","credit"]}],"s":["praise","distinction","fame","glory","acclaim","applause","credit"],"r":"[그리스어] kydos(glory/영광) → 탁월한 업적에 주는 영광 → 영광, 명예","type":"word","src":"Y"},{"id":4271,"vol":1,"day":33,"w":"label","m":"~에 꼬리표를 달다 / 분류하다 / ~를 …라고 부르다 / 꼬리표 / 음반 회사","p":[{"d":"~에 꼬리표를 달다 / 분류하다 / ~를 …라고 부르다 / 꼬리표 / 음반 회사","s":["sticker","tab","tag","brand","trademark","appellation","nomen","name","call","classify","record label"]}],"s":["classify","record label","sticker","tab","tag","brand","trademark","appellation","nomen","name","call"],"r":"[고대 프랑스어] label(ribbon/리본) → 매달린 표찰 → 라벨, 명칭을 붙이다","type":"word","src":"Y"},{"id":4272,"vol":1,"day":33,"w":"labor","m":"노동 / 수고 / 분만 / 노동하다 / 산고를 겪다 / 장황하게 설명하다","p":[],"s":[],"r":"","type":"word","src":"Y"},{"id":4273,"vol":1,"day":33,"w":"laborious","m":"힘든 / 열심히 일하는","p":[{"d":"힘든","s":["onerous","arduous"]},{"d":"열심히 일하는","s":["tedious","difficult","strenuous","exhausting"]}],"s":["onerous","arduous","tedious","difficult","strenuous","exhausting"],"r":"labor(work/노동) + -ious → 노동이 많이 드는 → 힘든, 근면한","type":"word","src":"Y"},{"id":4274,"vol":1,"day":33,"w":"labyrinth","m":"미로","p":[{"d":"미로","s":["maze"]}],"s":["maze"],"r":"[그리스어] labyrinthos(maze/미궁) → 미궁 → 미궁, 미로","type":"word","src":"Y"},{"id":4275,"vol":1,"day":33,"w":"lachrymose","m":"잘 우는 / 눈물 나게 하는","p":[{"d":"잘 우는 / 눈물 나게 하는","s":["sorrowful","tearful","weepy","emotional","sentimental"]}],"s":["sorrowful","tearful","weepy","emotional","sentimental"],"r":"lachry(tear/눈물) + -mose → 눈물이 많은 → 눈물을 잘 흘리는","type":"word","src":"Y"},{"id":4276,"vol":1,"day":33,"w":"lack","m":"결핍 / 부족 / ~이 결핍되다","p":[{"d":"결핍","s":["want"]},{"d":"부족 / ~이 결핍되다","s":["dearth","shortage"]}],"s":["want","dearth","shortage"],"r":"[중세 저지 독일어] lak(deficiency/부족) → 부족한 것 → 부족, 결핍","type":"word","src":"Y"},{"id":4277,"vol":1,"day":33,"w":"lackadaisical","m":"열의 없는 / 활기 없는","p":[{"d":"열의 없는 / 활기 없는","s":["languid","inert","lethargic","limp","listless","idle","indolent","lazy","negligent","remiss"]}],"s":["languid","inert","lethargic","limp","listless","idle","indolent","lazy","negligent","remiss"],"r":"lack(lack/부족) + a day(감탄사) + -sical → 아쉬워하며 힘없이 → 활기 없는, 나태한","type":"word","src":"Y"},{"id":4278,"vol":1,"day":33,"w":"lackluster","m":"활기 없는 / 광택 없는","p":[{"d":"활기 없는","s":["dull"]},{"d":"광택 없는","s":["dim","flat"]}],"s":["dull","dim","flat"],"r":"lack(lack/부족) + luster(luster/광택) → 광택이 부족한 → 광택이 없는, 활기 없는","type":"word","src":"Y"},{"id":4279,"vol":1,"day":33,"w":"laconic","m":"간결한 / 말수가 적은","p":[{"d":"간결한 / 말수가 적은","s":["brief","compact","concise","crisp","terse","succinct","taciturn","reticent"]}],"s":["concise","crisp","terse","succinct","taciturn","reticent","brief","compact"],"r":"Lacon(스파르타의 옛 이름, 말수 적은 것으로 유명) + -ic → 스파르타인처럼 말수가 적은 → 간결한","type":"word","src":"Y"},{"id":4280,"vol":1,"day":33,"w":"lactate","m":"젖을 분비하다 / 젖을 먹이다","p":[{"d":"젖을 분비하다 / 젖을 먹이다","s":["breast-feed"]}],"s":["breast-feed"],"r":"","type":"word","src":"Y"},{"id":4281,"vol":1,"day":33,"w":"lad","m":"젊은이 / 남자","p":[],"s":[],"r":"","type":"word","src":"Y"},{"id":4282,"vol":1,"day":33,"w":"ladder","m":"사다리 / 단계(지위의)","p":[],"s":[],"r":"","type":"word","src":"Y"},{"id":4283,"vol":1,"day":33,"w":"laden with","m":"~로 가득한","p":[{"d":"~로 가득한","s":["fraught with"]}],"s":["fraught with"],"r":"","type":"phrase","src":"Y"},{"id":4284,"vol":1,"day":33,"w":"lag","m":"꾸물거리다 / 지체되다","p":[{"d":"꾸물거리다","s":["linger"]},{"d":"지체되다","s":["fall behind","straggle","trail","dawdle"]}],"s":["linger","fall behind","straggle","trail","dawdle"],"r":"[스칸디나비아어] lagga(go slowly/천천히 가다) → 뒤처져 가다 → 처지다, 뒤떨어지다","type":"word","src":"Y"},{"id":4285,"vol":1,"day":33,"w":"laid-back","m":"느긋한 / 한가로운","p":[{"d":"느긋한","s":["relaxed"]}],"s":["relaxed"],"r":"","type":"word","src":"Y"},{"id":4286,"vol":1,"day":33,"w":"laissez-faire","m":"자유 방임적인 / 자유 방임주의","p":[{"d":"자유 방임적인","s":["permissive"]}],"s":["permissive"],"r":"[프랑스어] laisser(let/놓아두다) + faire(do/하다) → 하도록 놓아두다 → 자유방임주의","type":"word","src":"Y"},{"id":4287,"vol":1,"day":33,"w":"lambaste","m":"호되게 비난하다 / 세게 때리다","p":[{"d":"호되게 비난하다","s":["criticize harshly"]}],"s":["criticize harshly"],"r":"","type":"word","src":"Y"},{"id":4288,"vol":1,"day":33,"w":"lame","m":"절름발이의 / 불구의 / 설득력이 없는 / 불구로 만들다","p":[{"d":"절름발이의 / 불구의 / 설득력이 없는 / 불구로 만들다","s":["crippled","flimsy","inadequate"]}],"s":["crippled","flimsy","inadequate"],"r":"[고대 영어] lama(lame/절뚝거리는) → 절뚝거리는 → 다리를 저는, 설득력 없는","type":"word","src":"Y"},{"id":4289,"vol":1,"day":33,"w":"lamentable","m":"통탄할 / 슬픈","p":[{"d":"통탄할 / 슬픈","s":["sad"]}],"s":["sad"],"r":"","type":"word","src":"Y"},{"id":4290,"vol":1,"day":33,"w":"lampoon","m":"풍자하다","p":[{"d":"풍자하다","s":["satirize","burlesque","caricature","satire","mimic","mock","parody"]}],"s":["satirize","burlesque","caricature","satire","mimic","mock","parody"],"r":"[프랑스어] lampon(drink/마시다) → 술 마시며 빈정대다 → 풍자, 풍자하다","type":"word","src":"Y"},{"id":4291,"vol":1,"day":33,"w":"land","m":"획득하다 / 상륙시키다 / 착륙하다 / ~상태에 빠뜨리다","p":[{"d":"획득하다","s":["win"]}],"s":["win"],"r":"","type":"word","src":"Y"},{"id":4292,"vol":1,"day":33,"w":"land bridge","m":"육교(바다를 사이에 둔 지역을 연결한 육지)","p":[],"s":[],"r":"","type":"phrase","src":"Y"},{"id":4293,"vol":1,"day":33,"w":"landfill","m":"쓰레기 매립 / 쓰레기 매립지","p":[],"s":[],"r":"","type":"word","src":"Y"},{"id":4294,"vol":1,"day":33,"w":"landlord","m":"집주인 / 지주","p":[{"d":"집주인 / 지주","s":["landowner"]}],"s":["landowner"],"r":"","type":"word","src":"Y"},{"id":4295,"vol":1,"day":33,"w":"landmark","m":"경계표 / 획기적 사건 / 역사적 건물 / 획기적인","p":[{"d":"경계표 / 획기적 사건","s":["milestone"]},{"d":"역사적 건물 / 획기적인","s":["turning point","watershed"]}],"s":["milestone","turning point","watershed"],"r":"land(땅) + mark(표시) → 땅의 눈에 띄는 표시 → 주요지형물, 획기적 사건","type":"word","src":"Y"},{"id":4296,"vol":1,"day":33,"w":"landscape","m":"풍경","p":[{"d":"풍경","s":["scenery","outlook","prospect","scene","view"]}],"s":["scenery","outlook","prospect","scene","view"],"r":"land(land/땅) + scape(shape/형태) → 땅의 형태 → 풍경, 경치","type":"word","src":"Y"},{"id":4297,"vol":1,"day":33,"w":"landslide","m":"압승 / 산사태","p":[{"d":"압승 / 산사태","s":["avalanche","mudslide","overwhelming victory"]}],"s":["avalanche","mudslide","overwhelming victory"],"r":"land(land/땅) + slide(slide/미끄러지다) → 땅이 미끄러져 내리는 → 산사태, 압도적 승리","type":"word","src":"Y"},{"id":4298,"vol":1,"day":33,"w":"lane","m":"좁은 길 / 차선","p":[{"d":"좁은 길","s":["narrow road"]}],"s":["narrow road"],"r":"","type":"word","src":"Y"},{"id":4299,"vol":1,"day":33,"w":"languid","m":"무기력한 / 활기 없는 / 노곤한","p":[{"d":"무기력한 / 활기 없는","s":["listless","lethargic","sluggish"]},{"d":"노곤한","s":["languorous","halfhearted","lukewarm"]}],"s":["listless","lethargic","sluggish","languorous","halfhearted","lukewarm"],"r":"langu(weak/약한) + -id → 약한 성질 → 나른한, 열의 없는","type":"word","src":"Y"},{"id":4300,"vol":1,"day":33,"w":"languish","m":"쇠약해지다 / 시들다 / 방치되다 / 괴로운 생활을 하다","p":[{"d":"쇠약해지다","s":["decline"]},{"d":"시들다","s":["shrivel","wither","wilt"]},{"d":"방치되다 / 괴로운 생활을 하다","s":["weaken"]}],"s":["decline","shrivel","wither","wilt","weaken"],"r":"langu(weak/약한) + -ish → 약해지다 → 쇠약해지다, 시들다","type":"word","src":"Y"},{"id":4301,"vol":1,"day":33,"w":"lanky = lank","m":"호리호리한","p":[{"d":"호리호리한","s":["lean"]}],"s":["lean"],"r":"","type":"phrase","src":"Y"},{"id":4302,"vol":1,"day":33,"w":"lap","m":"무릎(앉은 상태에서의 양 허벅지 부분) / 한 바퀴(경주 트랙의) / 겹쳐 얹다 / 핥다 / 밀려오다","p":[{"d":"무릎(앉은 상태에서의 양 허벅지 부분) / 한 바퀴(경주 트랙의) / 겹쳐 얹다 / 핥다","s":["lick"]}],"s":["lick"],"r":"","type":"word","src":"Y"},{"id":4303,"vol":1,"day":33,"w":"lapse","m":"착오 / 일탈 / 통계 편차 / 하락 / 시간의 경과 / 실수하다 / 타락하다 / 소멸하다 [of]","p":[{"d":"착오","s":["oversight"]},{"d":"일탈","s":["deviation"]},{"d":"통계 편차 / 하락 / 시간의 경과","s":["passage"]},{"d":"실수하다 / 타락하다 / 소멸하다","s":["blunder","fault","mistake"]}],"s":["oversight","deviation","passage","blunder","fault","mistake"],"r":"laps(slip/미끄러지다) → 미끄러지듯 지나가다 → 경과, 실수","type":"word","src":"Y","pp":["of"]},{"id":4304,"vol":1,"day":33,"w":"larceny","m":"절도죄","p":[{"d":"절도죄","s":["theft","burglary","pilfering","purloining","robbery"]}],"s":["theft","burglary","pilfering","purloining","robbery"],"r":"larcin(theft/도둑질) + -y → 도둑질하는 것 → 절도죄","type":"word","src":"Y"},{"id":4305,"vol":1,"day":33,"w":"largess","m":"아낌없이 주기 / 선물","p":[{"d":"아낌없이 주기","s":["munificence","generosity"]},{"d":"선물","s":["openhandedness"]}],"s":["munificence","generosity","openhandedness"],"r":"larg(generous/후한) + -ess → 후하게 베푸는 것 → 아낌없이 줌, 선물","type":"word","src":"Y"},{"id":4306,"vol":1,"day":33,"w":"larva","m":"애벌레 / 유충","p":[{"d":"애벌레 / 유충","s":["caterpillar","grub"]}],"s":["caterpillar","grub"],"r":"[라틴어] larva(ghost/유령, 가면) → 성체가 되기 전 가면 쓴 모습 → 애벌레, 유충","type":"word","src":"Y"},{"id":4307,"vol":1,"day":33,"w":"lassitude","m":"무기력","p":[{"d":"무기력","s":["lethargy","sluggishness","languor","weariness"]}],"s":["lethargy","sluggishness","languor","weariness"],"r":"lass(weary/피곤한) + -itude → 피곤한 상태 → 나른함, 권태","type":"word","src":"Y"},{"id":4308,"vol":1,"day":33,"w":"last","m":"지속하다 / 오래 가다 / 가장 ~할 것 같지 않은","p":[],"s":[],"r":"","type":"word","src":"Y"},{"id":4309,"vol":1,"day":33,"w":"last but not least","m":"마지막에 말하긴 하지만 아주 중요한","p":[],"s":[],"r":"","type":"phrase","src":"Y"},{"id":4310,"vol":1,"day":33,"w":"last laugh","m":"최후의 승리","p":[],"s":[],"r":"","type":"phrase","src":"Y"},{"id":4311,"vol":1,"day":33,"w":"last name","m":"성(姓)","p":[{"d":"성(姓)","s":["family name","surname"]}],"s":["family name","surname"],"r":"","type":"phrase","src":"Y"},{"id":4312,"vol":1,"day":33,"w":"lasting","m":"영속하는 / 영구적인","p":[{"d":"영속하는 / 영구적인","s":["permanent"]}],"s":["permanent"],"r":"","type":"word","src":"Y"},{"id":4313,"vol":1,"day":33,"w":"latch onto","m":"이해하다 / ~에 달라붙다","p":[{"d":"이해하다","s":["comprehend"]}],"s":["comprehend"],"r":"","type":"phrase","src":"Y"},{"id":4314,"vol":1,"day":33,"w":"latent","m":"잠재한 / 잠복성의 / 숨은","p":[{"d":"잠재한 / 잠복성의 / 숨은","s":["hidden","dormant"]}],"s":["hidden","dormant"],"r":"lat(hide/숨다) + -ent → 숨어 있는 → 잠재적인","type":"word","src":"Y"},{"id":4315,"vol":1,"day":33,"w":"lateral","m":"옆의 / 측면의","p":[{"d":"옆의 / 측면의","s":["sideways","sideward"]}],"s":["sideways","sideward"],"r":"later(side/옆) + -al → 옆의 → 옆의, 측면의","type":"word","src":"Y"},{"id":4316,"vol":1,"day":33,"w":"latitude","m":"위도 / 허용 범위 / 자유","p":[{"d":"위도 / 허용 범위 / 자유","s":["freedom","leeway","scope"]}],"s":["freedom","leeway","scope"],"r":"lat(wide/넓은) + -itude → 넓은 정도 → 위도, 허용 범위","type":"word","src":"Y"},{"id":4317,"vol":1,"day":33,"w":"laud","m":"칭찬하다 / 칭찬 / 찬양","p":[{"d":"칭찬하다","s":["praise","compliment"]},{"d":"칭찬 / 찬양","s":["extol","commend","acclaim"]}],"s":["praise","compliment","extol","commend","acclaim"],"r":"laud(praise/칭찬) → 칭찬하다 → 찬양하다","type":"word","src":"Y"},{"id":4318,"vol":1,"day":33,"w":"laugh at","m":"웃다 / 비웃다","p":[],"s":[],"r":"","type":"phrase","src":"Y"},{"id":4319,"vol":1,"day":33,"w":"launch","m":"내보내다 / 발사하다 / 착수하다","p":[{"d":"내보내다 / 발사하다","s":["send up"]},{"d":"착수하다","s":["discharge","fire","shoot","begin","start"]}],"s":["send up","discharge","fire","shoot","begin","start"],"r":"[라틴어] lanceare(창을 던지다) → 힘껏 밀어 내보내다 → 진수시키다, 발사하다, 착수하다","type":"word","src":"Y"},{"id":4320,"vol":1,"day":33,"w":"launder","m":"세탁하다","p":[{"d":"세탁하다","s":["wash"]}],"s":["wash"],"r":"","type":"word","src":"Y"},{"id":4321,"vol":1,"day":33,"w":"lava","m":"용암","p":[],"s":[],"r":"","type":"word","src":"Y"},{"id":4322,"vol":1,"day":33,"w":"lavatory","m":"화장실 / 세면소","p":[],"s":[],"r":"","type":"word","src":"Y"},{"id":4323,"vol":1,"day":33,"w":"lavish","m":"후한 / 낭비하는 / 풍부한 / 아낌없이 주다 / 낭비하다 [on, upon]","p":[{"d":"후한","s":["generous"]},{"d":"낭비하는","s":["prodigal"]},{"d":"풍부한 / 아낌없이 주다","s":["shower"]},{"d":"낭비하다","s":["munificent","extravagant","wasteful","heap","pour"]}],"s":["generous","prodigal","shower","munificent","extravagant","wasteful","heap","pour"],"r":"lav(liberal/후한) + -ish → 후한 성질 → 마음이 후한, 사치스러운","type":"word","src":"Y","pp":["on","upon"]},{"id":4324,"vol":1,"day":33,"w":"law-abiding","m":"법을 지키는","p":[{"d":"법을 지키는","s":["non-criminal","observant"]}],"s":["non-criminal","observant"],"r":"","type":"word","src":"Y"},{"id":4325,"vol":1,"day":33,"w":"lawmaker","m":"국회의원 / 입법자","p":[{"d":"국회의원 / 입법자","s":["legislator"]}],"s":["legislator"],"r":"","type":"word","src":"Y"},{"id":4326,"vol":1,"day":33,"w":"lawn","m":"잔디밭","p":[],"s":[],"r":"","type":"word","src":"Y"},{"id":4327,"vol":1,"day":33,"w":"lax","m":"느슨한 / 엄격하지 않은","p":[{"d":"느슨한","s":["loose"]},{"d":"엄격하지 않은","s":["slack","lenient","permissive"]}],"s":["loose","slack","lenient","permissive"],"r":"[라틴어] laxus(loose/느슨한) → 느슨한 → 엄하지 않은, 해이한","type":"word","src":"Y"},{"id":4328,"vol":1,"day":33,"w":"lay","m":"평신도의 / 비전문가의 / 일반인의","p":[{"d":"평신도의 / 비전문가의","s":["nonprofessional"]}],"s":["nonprofessional"],"r":"","type":"word","src":"Y"},{"id":4329,"vol":1,"day":33,"w":"lay an egg","m":"실패하다(흥행에) / 알을 낳다","p":[],"s":[],"r":"","type":"phrase","src":"Y"},{"id":4330,"vol":1,"day":33,"w":"lay down","m":"규정하다 / 주장하다 / 내려놓다 / 버리다","p":[{"d":"규정하다","s":["prescribe"]}],"s":["prescribe"],"r":"","type":"phrase","src":"Y"}]